nhk-easy/__init__.py
nhk-easy/__main__.py
nhk-easy/api.py
nhk_easy/__init__.py
nhk_easy/__main__.py
nhk_easy/api.py
nhk_easy-0.0.9.dist-info/LICENSE
nhk_easy-0.0.9.dist-info/METADATA
nhk_easy-0.0.9.dist-info/WHEEL
nhk_easy-0.0.9.dist-info/entry_points.txt
nhk_easy-0.0.9.dist-info/top_level.txt
nhk_easy-0.0.9.dist-info/RECORD
