Metadata-Version: 2.1
Name: nhk-easy
Version: 0.0.9
Summary: Download today's news on https://www3.nhk.or.jp/news/easy/
Home-page: https://github.com/TianyiShi2001/nhk-easy
Author: Tianyi Shi
Author-email: ShiTianyi2001@outlook.com
License: MIT
Platform: UNKNOWN
Classifier: License :: OSI Approved :: MIT License
Classifier: Programming Language :: Python :: 3
Classifier: Programming Language :: Python :: 3.7
Classifier: Programming Language :: Python :: 3.8
Classifier: Programming Language :: Python :: 3.9
Requires-Python: >3.0.0
Requires-Dist: requests
Requires-Dist: lxml
